<?xml version="1.0"?>
<object name="1052872758" meta_type="Page Block">
 <property name="title">Footer</property>
 <property name="closed">False</property>
 <property name="width">100%</property>
 <property name="height">50px</property>
 <property name="maxcols">3</property>
 <property name="shape">NoBorder</property>
 <property name="color">Footergradient</property>
 <object name="1507015224" meta_type="Portlet Box Templet"/>
 <object name="1478167638" meta_type="Cell Block"/>
 <object name="773236679" meta_type="Cell Sizer"/>
 <object name="692327374" meta_type="Cell Sizer"/>
 <object name="1201053626" meta_type="Cell Sizer"/>
 <object name="743387521" meta_type="Cell Styler"/>
 <object name="993854963" meta_type="Cell Sizer"/>
 <object name="2110389968" meta_type="Cell Styler"/>
</object>
